claude_autoapprove/__init__.py
claude_autoapprove/claude_autoapprove.py
claude_autoapprove/inject.js
claude_autoapprove-0.2.5.dist-info/licenses/LICENSE
claude_autoapprove-0.2.5.dist-info/METADATA
claude_autoapprove-0.2.5.dist-info/WHEEL
claude_autoapprove-0.2.5.dist-info/entry_points.txt
claude_autoapprove-0.2.5.dist-info/top_level.txt
claude_autoapprove-0.2.5.dist-info/RECORD
