Metadata-Version: 2.4
Name: claude-autoapprove
Version: 0.2.5
Summary: A CLI tool to run Claude Desktop App and inject a hack to enable auto approve feature
Author: PYNESYS LLC
License: MIT
Project-URL: Homepage, https://github.com/PyneSys/claude_autoapprove
Project-URL: Repository, https://github.com/PyneSys/claude_autoapprove
Project-URL: Issues, https://github.com/PyneSys/claude_autoapprove/issues
Classifier: Programming Language :: Python :: 3
Classifier: License :: OSI Approved :: MIT License
Classifier: Operating System :: OS Independent
Requires-Python: >=3.11
License-File: LICENSE
Requires-Dist: requests>=2.31.0
Requires-Dist: websockets>=12.0
Dynamic: license-file
